Code/Parking_TB.v
module Parking (input car_entered, is_uni_car_entered, car_exited, is_uni_car_exited, clk,
    output reg uni_is_vacated_space, is_vacated_space,
    output reg [9:0] uni_parked_car, parked_car, uni_vacated_space, vacated_space);

    reg [9:0] university_capacity;
    wire hour;
    reg [9:0] public_capacity;
    reg [9:0] changed_capacity;
    integer timer;

    initial begin
        parked_car = 0;
        uni_vacated_space = 500;
        timer= 8;
        uni_parked_car = 0;
        university_capacity = 500;
        vacated_space = 200;
        public_capacity = 200;
    end

    Counter #(60) counter(clk, hour);
    always @(posedge hour or posedge clk) begin
        if (hour) begin
			   timer = timer + 1;
				if (timer % 24 == 14 || timer % 24 == 15) begin
					changed_capacity = (uni_vacated_space < 50) ? uni_vacated_space : 50;
					university_capacity = university_capacity - changed_capacity;
					uni_vacated_space = uni_vacated_space - changed_capacity;
					public_capacity = public_capacity + changed_capacity;
					vacated_space = vacated_space + changed_capacity;
				end else if (timer % 24 == 16) begin
					university_capacity = (uni_parked_car > 200) ? uni_parked_car : 200;
					public_capacity = 700 - university_capacity;
					vacated_space = public_capacity - parked_car;
					uni_vacated_space = university_capacity - uni_parked_car;
				end
		  end else if (clk) begin
				uni_is_vacated_space = (uni_vacated_space != 0) ? 1 : 0;
				is_vacated_space = (vacated_space != 0) ? 1 : 0;
				if (car_entered && is_uni_car_entered && uni_is_vacated_space) begin
					uni_parked_car = uni_parked_car + 1;
					uni_vacated_space = uni_vacated_space - 1;
				end else if (car_entered && !is_uni_car_entered && is_vacated_space) begin
					parked_car = parked_car + 1;
					vacated_space = vacated_space - 1;
				end else if (car_exited && is_uni_car_exited && uni_vacated_space > 0) begin
					uni_parked_car = uni_parked_car - 1;
					uni_vacated_space = uni_vacated_space + 1;
				end else if (car_exited && !is_uni_car_exited && vacated_space > 0) begin
					parked_car = parked_car - 1;
					vacated_space = vacated_space + 1;
				end
		  end
    end
endmodule
module Counter #(parameter n = 60) (input clk, output reg hour);
    integer count;
    
    initial begin
        hour = 0;
        count = 0;
    end

    always @(posedge clk) begin
        count = count + 1;
        if (count % n == 0)
            hour = 1;
        else
            hour = 0;
    end
endmodule
module Parking_TB();
    reg car_entered, is_uni_car_entered, car_exited, is_uni_car_exited,clk;
    wire uni_is_vacated_space, is_vacated_space;
    wire [9:0] uni_parked_car, parked_car, uni_vacated_space, vacated_space;

    always
        #5 clk = ~clk;

    Parking parking(car_entered, is_uni_car_entered, car_exited, is_uni_car_exited,clk,
    uni_is_vacated_space, is_vacated_space,uni_parked_car, parked_car, uni_vacated_space, vacated_space);

    initial begin
        car_entered=0;
        is_uni_car_entered=0;
        car_exited=0;
        is_uni_car_exited=0;
        clk=0;
        #300 car_entered = 1;
        #60 is_uni_car_entered = 1;
        #70 car_entered = 0; is_uni_car_entered = 0; car_exited = 1; is_uni_car_exited = 0;
        #60 car_entered = 1; is_uni_car_entered = 1; car_exited = 0; is_uni_car_exited = 1;
        #200 $finish();
    end

    initial begin
        $monitor("time= %t\n: car_entered = %b || is_uni_car_entered = %b || car_exited = %b || is_uni_car_exited = %b >>>>> uni_is_vacated_space = %d ||",
        $time, car_entered, is_uni_car_entered, car_exited, is_uni_car_exited,uni_is_vacated_space,
         "is_vacated_space = %d \n|| uni_parked_car = %d || parked_car = %d || uni_vacated_space = %d || vacated_space = %d",
         is_vacated_space,uni_parked_car, parked_car, uni_vacated_space, vacated_space);
    end
        initial begin
        $dumpfile("Parking.vcd");
        $dumpvars(0,Parking_TB);
    end
endmodule

doc/Parking.vcd
$date
	Thu Jun 27 00:39:07 2024
$end
$version
	Icarus Verilog
$end
$timescale
	1s
$end
$scope module Parking_TB $end
$var wire 10 ! vacated_space [9:0] $end
$var wire 10 " uni_vacated_space [9:0] $end
$var wire 10 # uni_parked_car [9:0] $end
$var wire 1 $ uni_is_vacated_space $end
$var wire 10 % parked_car [9:0] $end
$var wire 1 & is_vacated_space $end
$var reg 1 ' car_entered $end
$var reg 1 ( car_exited $end
$var reg 1 ) clk $end
$var reg 1 * is_uni_car_entered $end
$var reg 1 + is_uni_car_exited $end
$scope module parking $end
$var wire 1 ' car_entered $end
$var wire 1 ( car_exited $end
$var wire 1 ) clk $end
$var wire 1 * is_uni_car_entered $end
$var wire 1 + is_uni_car_exited $end
$var wire 1 , hour $end
$var reg 10 - changed_capacity [9:0] $end
$var reg 1 & is_vacated_space $end
$var reg 10 . parked_car [9:0] $end
$var reg 10 / public_capacity [9:0] $end
$var reg 1 $ uni_is_vacated_space $end
$var reg 10 0 uni_parked_car [9:0] $end
$var reg 10 1 uni_vacated_space [9:0] $end
$var reg 10 2 university_capacity [9:0] $end
$var reg 10 3 vacated_space [9:0] $end
$var integer 32 4 timer [31:0] $end
$scope module counter $end
$var wire 1 ) clk $end
$var reg 1 , hour $end
$var integer 32 5 count [31:0] $end
$upscope $end
$upscope $end
$upscope $end
$enddefinitions $end
#0
$dumpvars
b0 5
b1000 4
b11001000 3
b111110100 2
b111110100 1
b0 0
b11001000 /
b0 .
bx -
0,
0+
0*
0)
0(
0'
x&
b0 %
x$
b0 #
b111110100 "
b11001000 !
$end
#5
b1 5
1&
1$
1)
#10
0)
#15
b10 5
1)
#20
0)
#25
b11 5
1)
#30
0)
#35
b100 5
1)
#40
0)
#45
b101 5
1)
#50
0)
#55
b110 5
1)
#60
0)
#65
b111 5
1)
#70
0)
#75
b1000 5
1)
#80
0)
#85
b1001 5
1)
#90
0)
#95
b1010 5
1)
#100
0)
#105
b1011 5
1)
#110
0)
#115
b1100 5
1)
#120
0)
#125
b1101 5
1)
#130
0)
#135
b1110 5
1)
#140
0)
#145
b1111 5
1)
#150
0)
#155
b10000 5
1)
#160
0)
#165
b10001 5
1)
#170
0)
#175
b10010 5
1)
#180
0)
#185
b10011 5
1)
#190
0)
#195
b10100 5
1)
#200
0)
#205
b10101 5
1)
#210
0)
#215
b10110 5
1)
#220
0)
#225
b10111 5
1)
#230
0)
#235
b11000 5
1)
#240
0)
#245
b11001 5
1)
#250
0)
#255
b11010 5
1)
#260
0)
#265
b11011 5
1)
#270
0)
#275
b11100 5
1)
#280
0)
#285
b11101 5
1)
#290
0)
#295
b11110 5
1)
#300
0)
1'
#305
b11111 5
b11000111 !
b11000111 3
b1 %
b1 .
1)
#310
0)
#315
b100000 5
b11000110 !
b11000110 3
b10 %
b10 .
1)
#320
0)
#325
b100001 5
b11000101 !
b11000101 3
b11 %
b11 .
1)
#330
0)
#335
b100010 5
b11000100 !
b11000100 3
b100 %
b100 .
1)
#340
0)
#345
b100011 5
b11000011 !
b11000011 3
b101 %
b101 .
1)
#350
0)
#355
b100100 5
b11000010 !
b11000010 3
b110 %
b110 .
1)
#360
0)
1*
#365
b100101 5
b111110011 "
b111110011 1
b1 #
b1 0
1)
#370
0)
#375
b100110 5
b111110010 "
b111110010 1
b10 #
b10 0
1)
#380
0)
#385
b100111 5
b111110001 "
b111110001 1
b11 #
b11 0
1)
#390
0)
#395
b101000 5
b111110000 "
b111110000 1
b100 #
b100 0
1)
#400
0)
#405
b101001 5
b111101111 "
b111101111 1
b101 #
b101 0
1)
#410
0)
#415
b101010 5
b111101110 "
b111101110 1
b110 #
b110 0
1)
#420
0)
#425
b101011 5
b111101101 "
b111101101 1
b111 #
b111 0
1)
#430
0)
1(
0*
0'
#435
b101100 5
b11000011 !
b11000011 3
b101 %
b101 .
1)
#440
0)
#445
b101101 5
b11000100 !
b11000100 3
b100 %
b100 .
1)
#450
0)
#455
b101110 5
b11000101 !
b11000101 3
b11 %
b11 .
1)
#460
0)
#465
b101111 5
b11000110 !
b11000110 3
b10 %
b10 .
1)
#470
0)
#475
b110000 5
b11000111 !
b11000111 3
b1 %
b1 .
1)
#480
0)
#485
b110001 5
b11001000 !
b11001000 3
b0 %
b0 .
1)
#490
0)
#495
b110010 5
b11001001 !
b11001001 3
b1111111111 %
b1111111111 .
1)
#500
0)
1+
0(
1*
1'
#505
b110011 5
b111101100 "
b111101100 1
b1000 #
b1000 0
1)
#510
0)
#515
b110100 5
b111101011 "
b111101011 1
b1001 #
b1001 0
1)
#520
0)
#525
b110101 5
b111101010 "
b111101010 1
b1010 #
b1010 0
1)
#530
0)
#535
b110110 5
b111101001 "
b111101001 1
b1011 #
b1011 0
1)
#540
0)
#545
b110111 5
b111101000 "
b111101000 1
b1100 #
b1100 0
1)
#550
0)
#555
b111000 5
b111100111 "
b111100111 1
b1101 #
b1101 0
1)
#560
0)
#565
b111001 5
b111100110 "
b111100110 1
b1110 #
b1110 0
1)
#570
0)
#575
b111010 5
b111100101 "
b111100101 1
b1111 #
b1111 0
1)
#580
0)
#585
b111011 5
b111100100 "
b111100100 1
b10000 #
b10000 0
1)
#590
0)
#595
b1001 4
1,
b111100 5
b111100011 "
b111100011 1
b10001 #
b10001 0
1)
#600
0)
#605
0,
b111101 5
b1010 4
1)
#610
0)
#615
b111110 5
b111100010 "
b111100010 1
b10010 #
b10010 0
1)
#620
0)
#625
b111111 5
b111100001 "
b111100001 1
b10011 #
b10011 0
1)
#630
0)
#635
b1000000 5
b111100000 "
b111100000 1
b10100 #
b10100 0
1)
#640
0)
#645
b1000001 5
b111011111 "
b111011111 1
b10101 #
b10101 0
1)
#650
0)
#655
b1000010 5
b111011110 "
b111011110 1
b10110 #
b10110 0
1)
#660
0)
#665
b1000011 5
b111011101 "
b111011101 1
b10111 #
b10111 0
1)
#670
0)
#675
b1000100 5
b111011100 "
b111011100 1
b11000 #
b11000 0
1)
#680
0)
#685
b1000101 5
b111011011 "
b111011011 1
b11001 #
b11001 0
1)
#690
0)
#695
b1000110 5
b111011010 "
b111011010 1
b11010 #
b11010 0
1)
